rockrl/__init__.py
rockrl/tensorflow/__init__.py
rockrl/tensorflow/requirements.txt
rockrl/tensorflow/PPO/ppo.py
rockrl/tensorflow/examples/ppo/__init__.py
rockrl/tensorflow/examples/ppo/BipedalWalker-v3/BipedalWalker-v3.py
rockrl/tensorflow/examples/ppo/BipedalWalker-v3/BipedalWalker-v3_test.py
rockrl/tensorflow/examples/ppo/BipedalWalkerHardcore-v3/BipedalWalkerHardcore-v3.py
rockrl/tensorflow/examples/ppo/BipedalWalkerHardcore-v3/BipedalWalkerHardcore-v3_test.py
rockrl/tensorflow/examples/ppo/LunarLander-v2/LunarLander-v2.py
rockrl/tensorflow/examples/ppo/LunarLander-v2/LunarLander-v2_test.py
rockrl/utils/__init__.py
rockrl/utils/memory.py
rockrl/utils/misc.py
rockrl/utils/vectorizedEnv.py
rockrl-0.4.6.dist-info/LICENSE
rockrl-0.4.6.dist-info/METADATA
rockrl-0.4.6.dist-info/WHEEL
rockrl-0.4.6.dist-info/top_level.txt
rockrl-0.4.6.dist-info/RECORD
