Metadata-Version: 2.1
Name: rockrl
Version: 0.4.6
Summary: Reinformcement Learning library
Home-page: https://pylessons.com/
Author: PyLessons
Author-email: pythonlessons0@gmail.com
Project-URL: Source, https://github.com/pythonlessons/RockRL/
Project-URL: Tracker, https://github.com/pythonlessons/RockRL/issues
Requires-Python: >=3
License-File: LICENSE
Requires-Dist: numpy
Requires-Dist: pyyaml ==6.0
